ydb_mcp/__init__.py
ydb_mcp/__main__.py
ydb_mcp/connection.py
ydb_mcp/query.py
ydb_mcp/server.py
ydb_mcp/tool_manager.py
ydb_mcp/version.py
ydb_mcp-0.1.6.dist-info/licenses/LICENSE
ydb_mcp-0.1.6.dist-info/METADATA
ydb_mcp-0.1.6.dist-info/WHEEL
ydb_mcp-0.1.6.dist-info/entry_points.txt
ydb_mcp-0.1.6.dist-info/top_level.txt
ydb_mcp-0.1.6.dist-info/RECORD
