Metadata-Version: 2.4
Name: ydb-mcp
Version: 0.1.6
Summary: Model Context Protocol server for YDB DBMS
Author-email: YDB MCP Team <info@ydb.tech>
License: Apache 2.0
Classifier: Development Status :: 3 - Alpha
Classifier: Intended Audience :: Developers
Classifier: Programming Language :: Python :: 3
Classifier: Programming Language :: Python :: 3.10
Classifier: Programming Language :: Python :: 3.11
Classifier: Programming Language :: Python :: 3.12
Requires-Python: >=3.10
License-File: LICENSE
Requires-Dist: ydb>=3.21.0
Requires-Dist: mcp>=1.6.0
Provides-Extra: dev
Requires-Dist: pytest>=7.3.1; extra == "dev"
Requires-Dist: pytest-asyncio>=0.21.0; extra == "dev"
Requires-Dist: pytest-cov>=4.1.0; extra == "dev"
Requires-Dist: pytest-assume>=2.4.3; extra == "dev"
Requires-Dist: mypy>=1.3.0; extra == "dev"
Requires-Dist: ruff>=0.11.0; extra == "dev"
Requires-Dist: docker>=7.0.0; extra == "dev"
Dynamic: license-file
